hyperpod_custom_inference_template/__init__.py
hyperpod_custom_inference_template/registry.py
hyperpod_custom_inference_template/v1_0/__init__.py
hyperpod_custom_inference_template/v1_0/model.py
hyperpod_custom_inference_template/v1_0/schema.json
hyperpod_custom_inference_template/v1_0/template.py
hyperpod_custom_inference_template-1.0.2.dist-info/licenses/LICENSE
hyperpod_custom_inference_template-1.0.2.dist-info/METADATA
hyperpod_custom_inference_template-1.0.2.dist-info/WHEEL
hyperpod_custom_inference_template-1.0.2.dist-info/top_level.txt
hyperpod_custom_inference_template-1.0.2.dist-info/RECORD
