Metadata-Version: 2.4
Name: hyperpod-custom-inference-template
Version: 1.0.2
Summary: Versioned JSON-schema + Pydantic models for Custom configs
Author: Amazon Web Services
License: Apache-2.0
Requires-Python: >=3.8
License-File: LICENSE
Dynamic: license-file
